rscase/rscase.cpython-38-x86_64-linux-gnu.so
rscase/__init__.py
rscase-1.1.1.dist-info/METADATA
rscase-1.1.1.dist-info/RECORD
rscase-1.1.1.dist-info/WHEEL
rscase-1.1.1.dist-info/top_level.txt
