Metadata-Version: 2.1
Name: rscase
Version: 1.1.1
Summary: Python package for string case formatting; implemented in Rust.
Home-page: https://github.com/sondrelg/rs-case
Author: Sondre Lillebø Gundersen
Author-email: sondrelg@live.no
License: BSD
Download-URL: https://pypi.python.org/pypi/rscase
Keywords: snake camel pascal train kebab case
Platform: OS Independent
Classifier: Development Status :: 3 - Alpha
Classifier: Environment :: Web Environment
Classifier: Intended Audience :: Developers
Classifier: License :: OSI Approved :: BSD License
Classifier: Natural Language :: English
Classifier: Operating System :: OS Independent
Classifier: Programming Language :: Python
Classifier: Programming Language :: Python :: 3 :: Only
Classifier: Programming Language :: Python :: 3.8
Classifier: Programming Language :: Rust
Classifier: Topic :: Software Development :: Libraries :: Python Modules
Classifier: Topic :: Text Processing :: General
Requires-Dist: setuptools-rust (>=0.10.1)
Requires-Dist: wheel
Requires-Dist: setuptools
